fmodpy/__init__.py
fmodpy/fmodpy.py
fmodpy/potential_fmodpy_plan.py
fmodpy-0.0.6.dist-info/DESCRIPTION.rst
fmodpy-0.0.6.dist-info/METADATA
fmodpy-0.0.6.dist-info/RECORD
fmodpy-0.0.6.dist-info/WHEEL
fmodpy-0.0.6.dist-info/metadata.json
fmodpy-0.0.6.dist-info/top_level.txt
