Metadata-Version: 2.0
Name: fmodpy
Version: 0.0.6
Summary: A lightweight, efficient, highly automated, fortran wrapper for python.
Home-page: https://github.com/tchlux/fmodpy
Author: Thomas C.H. Lux
Author-email: tchlux@vt.edu
License: MIT
Download-URL: https://github.com/tchlux/fmodpy/archive/0.0.6.tar.gz
Keywords: python,python3,python27,fortran,wrapper
Platform: UNKNOWN
Classifier: Development Status :: 4 - Beta
Classifier: Intended Audience :: Developers
Classifier: Topic :: Software Development :: Build Tools
Classifier: License :: OSI Approved :: MIT License
Classifier: Programming Language :: Python :: 2.7
Classifier: Programming Language :: Python :: 3
Classifier: Programming Language :: Python :: 3.2
Classifier: Programming Language :: Python :: 3.3
Classifier: Programming Language :: Python :: 3.4
Classifier: Programming Language :: Python :: 3.5
Classifier: Programming Language :: Python :: 3.6
Classifier: Programming Language :: Python :: 3.7
Requires-Python: >=2.7
Requires-Dist: numpy (>=1.11)
